feincms3_meta/__init__.py
feincms3_meta/fields.py
feincms3_meta/models.py
feincms3_meta/utils.py
feincms3_meta/locale/de/LC_MESSAGES/django.mo
feincms3_meta/locale/de/LC_MESSAGES/django.po
feincms3_meta-4.6.0.dist-info/METADATA
feincms3_meta-4.6.0.dist-info/WHEEL
feincms3_meta-4.6.0.dist-info/licenses/LICENSE
feincms3_meta-4.6.0.dist-info/RECORD
